sc_libra/__init__.py
sc_libra/main.py
sc_libra/supp_functions_R.R
sc_libra-0.0.48.dist-info/METADATA
sc_libra-0.0.48.dist-info/WHEEL
sc_libra-0.0.48.dist-info/top_level.txt
sc_libra-0.0.48.dist-info/RECORD
