Metadata-Version: 2.1
Name: sc-libra
Version: 0.0.48
Summary: LIBRA package
Home-page: UNKNOWN
Author: Xabier Martinez de Morentin
Author-email: <xabiermm1@gmail.com>
License: UNKNOWN
Keywords: python,singlecell,sc,integration,prediction,pipeline
Platform: UNKNOWN
Classifier: Development Status :: 1 - Planning
Classifier: Intended Audience :: Developers
Classifier: Programming Language :: Python :: 3
Classifier: Operating System :: Unix
Classifier: Operating System :: MacOS :: MacOS X
Classifier: Operating System :: Microsoft :: Windows
Requires-Dist: anndata
Requires-Dist: numpy
Requires-Dist: pandas
Requires-Dist: leidenalg
Requires-Dist: tensorflow
Requires-Dist: keras
Requires-Dist: scanpy
Requires-Dist: scipy
Requires-Dist: sklearn
Requires-Dist: rpy2
